{
  "project_info": {
    "project_number": "555401462181",
    "project_id": "jobportalnew-a049b",
    "storage_bucket": "jobportalnew-a049b.appspot.com"
  },
  "client": [
    {
      "client_info": {
        "mobilesdk_app_id": "1:555401462181:android:c3da4860cd17774b71684c",
        "android_client_info": {
          "package_name": "com.example.job_portal_app"
        }
      },
      "oauth_client": [],
      "api_key": [
        {
          "current_key": "AIzaSyAwkvmAKwq_z970sH7wviWOqaoioRbRZhg"
        }
      ],
      "services": {
        "appinvite_service": {
          "other_platform_oauth_client": []
        }
      }
    }
  ],
  "configuration_version": "1"
}